venvexec/__main__.py
venvexec-0.1.0.dist-info/licenses/LICENSE
venvexec-0.1.0.dist-info/METADATA
venvexec-0.1.0.dist-info/WHEEL
venvexec-0.1.0.dist-info/entry_points.txt
venvexec-0.1.0.dist-info/top_level.txt
venvexec-0.1.0.dist-info/RECORD
