Metadata-Version: 2.4
Name: venvexec
Version: 0.1.0
Summary: Run commands always inside a central virtual environment
Author-email: kkyian <kkyian@icloud.com>
Requires-Python: >=3.7
License-File: LICENSE
Dynamic: license-file
